asset_store/__init__.py
asset_store/repository/repository.py
asset_store/repository/repository_type.py
asset_store/repository/neo4j/__init__.py
asset_store/repository/neo4j/edge.py
asset_store/repository/neo4j/edge_tag.py
asset_store/repository/neo4j/entity.py
asset_store/repository/neo4j/entity_tag.py
asset_store/repository/neo4j/neo_repository.py
asset_store/types/__init__.py
asset_store/types/edge.py
asset_store/types/edge_tag.py
asset_store/types/entity.py
asset_store/types/entity_tag.py
open_asset_store-0.0.2.dist-info/METADATA
open_asset_store-0.0.2.dist-info/WHEEL
open_asset_store-0.0.2.dist-info/licenses/LICENSE
open_asset_store-0.0.2.dist-info/RECORD
